peaksql/__init__.py
peaksql/database.py
peaksql/tables.py
peaksql/util.py
peaksql/datasets/__init__.py
peaksql/datasets/base.py
peaksql/datasets/bed.py
peaksql/datasets/bedgraph.py
peaksql/datasets/labeler.py
peaksql/datasets/narrowpeak.py
peaksql-0.0.4.dist-info/LICENSE
peaksql-0.0.4.dist-info/METADATA
peaksql-0.0.4.dist-info/WHEEL
peaksql-0.0.4.dist-info/top_level.txt
peaksql-0.0.4.dist-info/RECORD
