Metadata-Version: 2.1
Name: peaksql
Version: 0.0.4
Summary: TODO: add peaksq description
Home-page: https://github.com/vanheeringen-lab/peaksql
Author: ['Maarten van der Sande <maartenvandersande@hotmail.com>']
License: MIT
Platform: UNKNOWN
Classifier: Development Status :: 1 - Planning
Classifier: Intended Audience :: Developers
Classifier: Intended Audience :: Science/Research
Classifier: License :: OSI Approved :: MIT License
Classifier: Operating System :: POSIX :: Linux
Classifier: Operating System :: MacOS :: MacOS X
Classifier: Programming Language :: Python
Classifier: Programming Language :: Python :: 3
Classifier: Topic :: Scientific/Engineering :: Bio-Informatics
Requires-Python: >3.7
Requires-Dist: pyfaidx
Requires-Dist: numba
Requires-Dist: numpy
Requires-Dist: pandas
